alembic_clamp/__init__.py
alembic_clamp/clamp.py
alembic_clamp/click_commands.py
retort/__init__.py
alembic_clamp-0.1.0.dist-info/METADATA
alembic_clamp-0.1.0.dist-info/WHEEL
alembic_clamp-0.1.0.dist-info/top_level.txt
alembic_clamp-0.1.0.dist-info/RECORD
