Metadata-Version: 2.1
Name: alembic-clamp
Version: 0.1.0
Summary: Configurable wrapper around alembic (SQLAlchemy migration tool)
Home-page: https://github.com/ods/alembic-clamp
Author: Denis Otkidach
Author-email: denis.otkidach@gmail.com
License: MIT
Platform: UNKNOWN
Requires-Dist: alembic (>=1.4.2)
Requires-Dist: sqlalchemy (>=1.3.17)
Provides-Extra: click
Requires-Dist: click (>=7.0) ; extra == 'click'
